hackernews.py
hackernews_python-0.3.1.dist-info/DESCRIPTION.rst
hackernews_python-0.3.1.dist-info/METADATA
hackernews_python-0.3.1.dist-info/metadata.json
hackernews_python-0.3.1.dist-info/RECORD
hackernews_python-0.3.1.dist-info/top_level.txt
hackernews_python-0.3.1.dist-info/WHEEL
